CHANGES
LICENSE
MANIFEST.in
README
setup.py
demo/benchmark.py
demo/demo1.py
demo/demo2.py
demo/demo3.py
demo/math_demo.py
demo/notebook.py
wxtextview/__init__.py
wxtextview/boxes.py
wxtextview/builder.py
wxtextview/linewrap.py
wxtextview/rect.py
wxtextview/simplelayout.py
wxtextview/testdevice.py
wxtextview/testing.py
wxtextview/textview.py
wxtextview/wxdevice.py
wxtextview/wxtextview.py
wxtextview.egg-info/PKG-INFO
wxtextview.egg-info/SOURCES.txt
wxtextview.egg-info/dependency_links.txt
wxtextview.egg-info/requires.txt
wxtextview.egg-info/top_level.txt