Metadata-Version: 1.0
Name: wxtextview
Version: 0.3.6
Summary: A styled text widget for wxpython.
Home-page: https://pypi.python.org/pypi/wxtextview/
Author: C. Ecker
Author-email: textmodelview@gmail.com
License: BSD
Platform: any
